{
  "updatedTime": 29103644,
  "creator": "ProfiPoint",
  "goal": [4,0,90],
  "mapSize": [24,12],
  "creationTime": 0,
  "maxArrows": 20,
  "defaultLevel": false,
  "start": [23,8,0],
  "enemies": {

  },
  "timeLimit": 70,
  "tiles": {
    "18-6": 1,
    "10-5": 2,
    "12-3": 2,
    "10-4": 1,
    "12-2": 1,
    "10-3": 2,
    "10-2": 1,
    "18-5": 2,
    "16-6": 1,
    "18-4": 1,
    "3-3": 1,
    "18-3": 2,
    "16-5": 2,
    "3-4": 2,
    "14-6": 1,
    "18-2": 1,
    "16-4": 1,
    "5-3": 1,
    "3-5": 1,
    "16-3": 2,
    "14-5": 2,
    "3-6": 2,
    "12-6": 1,
    "16-2": 1,
    "14-4": 1,
    "3-7": 1,
    "3-8": 2,
    "14-3": 2,
    "12-5": 2,
    "9-2": 2,
    "10-6": 1,
    "14-2": 1,
    "12-4": 1,
    "9-3": 1,
    "5-8": 2,
    "9-4": 2,
    "9-5": 1,
    "7-8": 2,
    "9-6": 2,
    "9-7": 1,
    "9-8": 2,
    "21-4": 2,
    "21-2": 2,
    "23-8": 2,
    "21-6": 2,
    "19-6": 2,
    "13-2": 2,
    "11-4": 2,
    "11-2": 2,
    "4-0": 1,
    "17-6": 2,
    "19-4": 2,
    "2-3": 2,
    "4-1": 2,
    "2-4": 1,
    "4-2": 1,
    "15-6": 2,
    "19-2": 2,
    "17-4": 2,
    "4-3": 2,
    "2-5": 2,
    "2-6": 1,
    "13-6": 2,
    "17-2": 2,
    "15-4": 2,
    "6-3": 2,
    "2-7": 2,
    "2-8": 1,
    "6-4": 1,
    "11-6": 2,
    "15-2": 2,
    "13-4": 2,
    "6-5": 2,
    "4-8": 1,
    "6-6": 1,
    "6-7": 2,
    "6-8": 1,
    "8-8": 1,
    "20-6": 1,
    "22-4": 1,
    "22-3": 2,
    "20-5": 2,
    "22-2": 1,
    "20-4": 1,
    "20-3": 2,
    "20-2": 1,
    "22-8": 1,
    "22-7": 2,
    "22-6": 1,
    "22-5": 2
  },
  "creatorUpdated": "ProfiPoint",
  "goalSheep": 10,
  "items": [
    [9,2,0,1],
    [10,2,0,1],
    [11,2,0,1],
    [12,2,0,1],
    [13,2,0,1],
    [14,2,0,1],
    [15,2,0,1],
    [16,2,0,1],
    [17,2,0,1],
    [18,2,0,1],
    [19,2,0,1],
    [20,2,0,1],
    [21,2,0,1],
    [22,2,0,1],
    [20,3,0,1],
    [20,4,0,1],
    [20,5,0,1],
    [18,4,0,1],
    [18,5,0,1],
    [18,3,0,1],
    [16,3,0,1],
    [16,4,0,1],
    [16,5,0,1],
    [14,3,0,1],
    [14,4,0,1],
    [14,5,0,1],
    [12,3,0,1],
    [12,4,0,1],
    [12,5,0,1],
    [11,4,0,1],
    [10,3,0,1],
    [10,4,0,1],
    [9,3,0,1],
    [9,4,0,1],
    [9,5,0,1],
    [10,5,0,1],
    [13,4,0,1],
    [15,4,0,1],
    [17,4,0,1],
    [19,4,0,1],
    [21,4,0,1],
    [22,4,0,1],
    [22,3,0,1],
    [22,5,0,1],
    [22,6,0,1],
    [21,6,0,1],
    [20,6,0,1],
    [19,6,0,1],
    [18,6,0,1],
    [17,6,0,1],
    [16,6,0,1],
    [15,6,0,1],
    [14,6,0,1],
    [13,6,0,1],
    [12,6,0,1],
    [11,6,0,1],
    [10,6,0,1],
    [9,6,0,1],
    [2,6,0,1],
    [2,5,0,1],
    [2,4,0,1],
    [2,7,0,1]
  ],
  "sheep": 10
}